bloomyai/__init__.py
bloomyai/_config.py
bloomyai/core.py
bloomyai-0.0.3.dist-info/METADATA
bloomyai-0.0.3.dist-info/WHEEL
bloomyai-0.0.3.dist-info/top_level.txt
bloomyai-0.0.3.dist-info/RECORD
