Metadata-Version: 2.4
Name: bloomyai
Version: 0.0.3
Summary: A minimal Python library for uploading files to DO Spaces or locally.
Author-email: Aleksandr Karpov <akarpov.work@gmail.com>
License-Expression: MIT
Classifier: Programming Language :: Python :: 3
Classifier: Operating System :: OS Independent
Requires-Python: >=3.7
Requires-Dist: requests
